Metadata-Version: 2.4
Name: tobes-ui
Version: 0.3.1
Summary: Totally Bearable Spectrometer UI
Author-email: Michal Jirků <box@wejn.org>
License-Expression: GPL-3.0
Project-URL: Homepage, https://github.com/wejn/tobes-ui
Requires-Python: >=3.10
License-File: LICENSE.txt
Requires-Dist: colour-science[optional]
Requires-Dist: matplotlib
Requires-Dist: pyserial
Requires-Dist: scipy>=1.15.3
Provides-Extra: ocean
Requires-Dist: seabreeze; extra == "ocean"
Dynamic: license-file
